slackclipper.py
slackclipper_runner.py
slackclipper-0.4.1.dist-info/licenses/LICENSE
slackclipper-0.4.1.dist-info/METADATA
slackclipper-0.4.1.dist-info/WHEEL
slackclipper-0.4.1.dist-info/entry_points.txt
slackclipper-0.4.1.dist-info/top_level.txt
slackclipper-0.4.1.dist-info/RECORD
