Metadata-Version: 2.4
Name: slackclipper
Version: 0.4.1
Summary: Copy the contents of a Slack thread.
Author-email: Heath Raftery <heath@empirical.ee>
License-Expression: GPL-3.0-only
Project-URL: Repository, https://github.com/hraftery/slackclipper
Classifier: Development Status :: 4 - Beta
Classifier: Environment :: Console
Classifier: Programming Language :: Python :: 3
Classifier: Programming Language :: Python :: 3.7
Classifier: Intended Audience :: Developers
Classifier: Topic :: Software Development :: Libraries
Classifier: Topic :: Utilities
Requires-Python: >=3.7
License-File: LICENSE
Requires-Dist: slacktokens
Requires-Dist: requests==2.27.1
Requires-Dist: pyperclip==1.8.2
Requires-Dist: emoji==2.14.1
Dynamic: license-file
